parsify/__init__.py
parsify/parsify.py
parsify-3.8.dist-info/LICENSE
parsify-3.8.dist-info/METADATA
parsify-3.8.dist-info/WHEEL
parsify-3.8.dist-info/top_level.txt
parsify-3.8.dist-info/RECORD
