Metadata-Version: 2.1
Name: parsify
Version: 3.8
Summary: Parsing tool for massive parsing - stop writing many single parsers.
Home-page: https://github.com/lukasanukvari/parsify
Author: Luka Sosiashvili
Author-email: luksosiashvili@gmail.com
License: MIT License
Classifier: Programming Language :: Python :: 3
Classifier: License :: OSI Approved :: MIT License
Classifier: Operating System :: OS Independent
Requires-Python: >=3.8
License-File: LICENSE
Requires-Dist: requests
